ladim_plugins/__init__.py
ladim_plugins/chemicals/README.md
ladim_plugins/chemicals/__init__.py
ladim_plugins/chemicals/forcing.nc
ladim_plugins/chemicals/gridforce.py
ladim_plugins/chemicals/ibm.py
ladim_plugins/chemicals/ladim.yaml
ladim_plugins/chemicals/out.nc
ladim_plugins/chemicals/out.nc.yaml
ladim_plugins/chemicals/particles.rls
ladim_plugins/chemicals/test_chemicals.py
ladim_plugins/egg/README.md
ladim_plugins/egg/__init__.py
ladim_plugins/egg/forcing.nc
ladim_plugins/egg/ibm.py
ladim_plugins/egg/ladim.yaml
ladim_plugins/egg/out.nc
ladim_plugins/egg/out.nc.yaml
ladim_plugins/egg/particles.rls
ladim_plugins/egg/svim_ladim.yaml
ladim_plugins/egg/svim_make_release.m
ladim_plugins/egg/svim_particles.rls
ladim_plugins/larvae/README.md
ladim_plugins/larvae/__init__.py
ladim_plugins/larvae/forcing.nc
ladim_plugins/larvae/ibm.py
ladim_plugins/larvae/ladim.yaml
ladim_plugins/larvae/out.nc
ladim_plugins/larvae/out.rls
ladim_plugins/larvae/particles.rls
ladim_plugins/larvae/release.yaml
ladim_plugins/larvae/test_ibm.py
ladim_plugins/lunar_eel/README.md
ladim_plugins/lunar_eel/__init__.py
ladim_plugins/lunar_eel/de421.bsp
ladim_plugins/lunar_eel/forcing.nc
ladim_plugins/lunar_eel/ibm.py
ladim_plugins/lunar_eel/ladim.yaml
ladim_plugins/lunar_eel/out.nc
ladim_plugins/lunar_eel/out.nc.yaml
ladim_plugins/lunar_eel/particles.rls
ladim_plugins/mine/README.md
ladim_plugins/mine/__init__.py
ladim_plugins/mine/forcing.nc
ladim_plugins/mine/ibm.py
ladim_plugins/mine/ladim.yaml
ladim_plugins/mine/out.nc
ladim_plugins/mine/out.nc.yaml
ladim_plugins/mine/particles.rls
ladim_plugins/nk2d/README.md
ladim_plugins/nk2d/__init__.py
ladim_plugins/nk2d/forcing.nc
ladim_plugins/nk2d/gridforce.py
ladim_plugins/nk2d/ladim.yaml
ladim_plugins/nk2d/out.nc
ladim_plugins/nk2d/out.nc.yaml
ladim_plugins/nk2d/particles.rls
ladim_plugins/release/README.md
ladim_plugins/release/__init__.py
ladim_plugins/release/__main__.py
ladim_plugins/release/farms.py
ladim_plugins/release/makrel.py
ladim_plugins-2.9.1.dist-info/licenses/LICENSE
ladim_plugins-2.9.1.dist-info/METADATA
ladim_plugins-2.9.1.dist-info/WHEEL
ladim_plugins-2.9.1.dist-info/entry_points.txt
ladim_plugins-2.9.1.dist-info/top_level.txt
ladim_plugins-2.9.1.dist-info/RECORD
