Metadata-Version: 2.4
Name: ladim_plugins
Version: 2.9.1
Summary: Plugins for LADiM
Home-page: https://github.com/pnsaevik/ladim_plugins
Author: Pål Næverlid Sævik
Author-email: paal.naeverlid.saevik@hi.no
License: MIT
Classifier: Development Status :: 5 - Production/Stable
Classifier: Intended Audience :: Science/Research
Classifier: Topic :: Software Development :: Build Tools
Classifier: License :: OSI Approved :: MIT License
Classifier: Programming Language :: Python :: 3.8
Classifier: Programming Language :: Python :: 3.9
Classifier: Programming Language :: Python :: 3.10
Classifier: Programming Language :: Python :: 3.11
Classifier: Programming Language :: Python :: 3.12
Classifier: Programming Language :: Python :: 3.13
Classifier: Operating System :: OS Independent
Requires-Python: >=3.7
License-File: LICENSE
Requires-Dist: cftime
Requires-Dist: jinja2
Requires-Dist: ladim
Requires-Dist: netCDF4
Requires-Dist: numpy
Requires-Dist: pandas
Requires-Dist: pydap
Requires-Dist: pyarrow
Requires-Dist: pyproj
Requires-Dist: pytest
Requires-Dist: pyyaml
Requires-Dist: requests
Requires-Dist: scipy
Requires-Dist: skyfield
Requires-Dist: triangle
Requires-Dist: xarray
Dynamic: license-file
